cds_trytond_account_ca_gifi-4.6.0.dist-info/DESCRIPTION.rst
cds_trytond_account_ca_gifi-4.6.0.dist-info/METADATA
cds_trytond_account_ca_gifi-4.6.0.dist-info/RECORD
cds_trytond_account_ca_gifi-4.6.0.dist-info/WHEEL
cds_trytond_account_ca_gifi-4.6.0.dist-info/entry_points.txt
cds_trytond_account_ca_gifi-4.6.0.dist-info/metadata.json
cds_trytond_account_ca_gifi-4.6.0.dist-info/top_level.txt
trytond/modules/account_ca_gifi/__init__.py
trytond/modules/account_ca_gifi/account.py
trytond/modules/account_ca_gifi/account_ca.xml
trytond/modules/account_ca_gifi/tax_ca.xml
trytond/modules/account_ca_gifi/tryton.cfg
trytond/modules/account_ca_gifi/tests/__init__.py
trytond/modules/account_ca_gifi/tests/test_account_ca_gifi.py
