Metadata-Version: 2.0
Name: cds-trytond-account-ca-gifi
Version: 4.6.0
Summary: Tryton module with Canadian GIFI-based chart of accounts
Home-page: https://src.coalesco.ca/tryton/modules/cds_trytond_account_ca_gifi
Author: Tryton
Author-email: it@coalesco.ca
License: GPL-3
Download-URL: https://src.coalesco.ca/tryton/modules/cds_trytond_account_ca_gifi/archive/tip.zip
Keywords: tryton account chart canada gifi
Platform: UNKNOWN
Classifier: Development Status :: 5 - Production/Stable
Classifier: Environment :: Plugins
Classifier: Framework :: Tryton
Classifier: Intended Audience :: Developers
Classifier: Intended Audience :: Financial and Insurance Industry
Classifier: Intended Audience :: Legal Industry
Classifier: License :: OSI Approved :: GNU General Public License (GPL)
Classifier: Natural Language :: English
Classifier: Natural Language :: French
Classifier: Operating System :: OS Independent
Classifier: Programming Language :: Python :: 2.7
Classifier: Programming Language :: Python :: 3.3
Classifier: Programming Language :: Python :: 3.4
Classifier: Programming Language :: Python :: 3.5
Classifier: Programming Language :: Python :: Implementation :: CPython
Classifier: Programming Language :: Python :: Implementation :: PyPy
Classifier: Topic :: Office/Business
Classifier: Topic :: Office/Business :: Financial :: Accounting
Requires-Dist: trytond-account (<4.7,>=4.6)
Requires-Dist: trytond (<4.7,>=4.6)
